mtgclient/__init__.py
mtgclient/business_client.py
mtgclient/db_client.py
mtgclient-0.0.2.dist-info/METADATA
mtgclient-0.0.2.dist-info/WHEEL
mtgclient-0.0.2.dist-info/licenses/LICENSE
mtgclient-0.0.2.dist-info/RECORD
